.DS_Store
SpotifyCLI/__init__.py
SpotifyCLI-0.1.0.data/scripts/SpotifyCLI
SpotifyCLI-0.1.0.dist-info/METADATA
SpotifyCLI-0.1.0.dist-info/WHEEL
SpotifyCLI-0.1.0.dist-info/top_level.txt
SpotifyCLI-0.1.0.dist-info/RECORD
