Metadata-Version: 2.1
Name: SpotifyCLI
Version: 0.1.0
Summary: This program controls Spotify!
Home-page: https://github.com/ivyjsgit/Spotify-CLI
Author: Ivy Jackson
Author-email: ivyjs@hendrix.edu
License: UNKNOWN
Platform: UNKNOWN
Classifier: Programming Language :: Python :: 3
Classifier: Operating System :: OS Independent
